README.txt
setup.py
martINI.egg-info/PKG-INFO
martINI.egg-info/SOURCES.txt
martINI.egg-info/dependency_links.txt
martINI.egg-info/entry_points.txt
martINI.egg-info/not-zip-safe
martINI.egg-info/requires.txt
martINI.egg-info/top_level.txt
martini/__init__.py
martini/config.py
martini/main.py
martini/odict.py
martini/utils.py
martini/web.py