Metadata-Version: 1.0
Name: martINI
Version: 0.6
Summary: edit .ini files from the command line
Home-page: http://k0s.org/hg/martINI
Author: Jeff Hammel
Author-email: k0scist@gmail.com
License: GPL
Keywords: ini cli
Platform: UNKNOWN
